rakuten_do_dbt_processor/__init__.py
rakuten_do_dbt_processor/processor.py
dbt_processor-0.1.0.dist-info/LICENSE
dbt_processor-0.1.0.dist-info/METADATA
dbt_processor-0.1.0.dist-info/WHEEL
dbt_processor-0.1.0.dist-info/entry_points.txt
dbt_processor-0.1.0.dist-info/top_level.txt
dbt_processor-0.1.0.dist-info/RECORD
