Metadata-Version: 2.1
Name: dbt-processor
Version: 0.1.0
Summary: A package to process dbt logs into Rakuten DO platform
Home-page: https://github.com/yourusername/dbt_processor
Author: Rakuten DO India
Author-email: ankur.kumar@rakuten.com
Classifier: Programming Language :: Python :: 3
Classifier: License :: OSI Approved :: MIT License
Classifier: Operating System :: OS Independent
Requires-Python: >=3.6
License-File: LICENSE
